bcm_connection/__init__.py
bcm_connection/bcm.py
bcm_connection/models.py
bcm_connection/utils.py
starlyng_bcm_connection-0.1.4.dist-info/METADATA
starlyng_bcm_connection-0.1.4.dist-info/WHEEL
starlyng_bcm_connection-0.1.4.dist-info/top_level.txt
starlyng_bcm_connection-0.1.4.dist-info/RECORD
